pimpmyrice/__init__.py
pimpmyrice/__main__.py
pimpmyrice/args.py
pimpmyrice/cli.py
pimpmyrice/color_extract.py
pimpmyrice/colors.py
pimpmyrice/completions.py
pimpmyrice/config_paths.py
pimpmyrice/doc.py
pimpmyrice/edit_args.py
pimpmyrice/events.py
pimpmyrice/exceptions.py
pimpmyrice/files.py
pimpmyrice/logger.py
pimpmyrice/module.py
pimpmyrice/module_utils.py
pimpmyrice/parsers.py
pimpmyrice/py.typed
pimpmyrice/schemas.py
pimpmyrice/template.py
pimpmyrice/theme.py
pimpmyrice/theme_utils.py
pimpmyrice/utils.py
pimpmyrice/assets/__init__.py
pimpmyrice/assets/default_base_style.json
pimpmyrice/palette_generators/__init__.py
pimpmyrice/palette_generators/dark.py
pimpmyrice/palette_generators/light.py
pimpmyrice-0.4.3.dist-info/licenses/LICENSE
pimpmyrice-0.4.3.dist-info/METADATA
pimpmyrice-0.4.3.dist-info/WHEEL
pimpmyrice-0.4.3.dist-info/entry_points.txt
pimpmyrice-0.4.3.dist-info/top_level.txt
pimpmyrice-0.4.3.dist-info/RECORD
