Metadata-Version: 2.4
Name: pimpmyrice
Version: 0.4.3
Summary: The overkill theme manager
Author-email: daddodev <daddodev@gmail.com>
License: MIT
Project-URL: Homepage, https://github.com/daddodev/pimpmyrice
Project-URL: Bug Tracker, https://github.com/daddodev/pimpmyrice/issues
Classifier: Programming Language :: Python :: 3
Classifier: License :: OSI Approved :: MIT License
Classifier: Operating System :: OS Independent
Requires-Python: >=3.10
License-File: LICENSE
Requires-Dist: rich
Requires-Dist: docopt
Requires-Dist: pyyaml
Requires-Dist: jinja2
Requires-Dist: requests
Requires-Dist: psutil
Requires-Dist: numpy
Requires-Dist: pillow
Requires-Dist: pydantic
Requires-Dist: typing_extensions
Provides-Extra: dev
Requires-Dist: python-lsp-server; extra == "dev"
Requires-Dist: ruff; extra == "dev"
Requires-Dist: mypy; extra == "dev"
Requires-Dist: isort; extra == "dev"
Requires-Dist: pytest; extra == "dev"
Requires-Dist: pytest-asyncio; extra == "dev"
Requires-Dist: types-requests; extra == "dev"
Requires-Dist: types-PyYAML; extra == "dev"
Dynamic: license-file
